{
  "report": [
    {
      "day": "DAY 1",
      "title": "Day 1 - 前言",
      "url": "https://ithelp.ithome.com.tw/articles/10314442",
      "file": "ironman-6262-days/day01-day-1-前言.md",
      "sections": 4,
      "raw_len": 1301,
      "md_len": 1313,
      "coverage_ratio": 1.009,
      "images_in_article": 0,
      "images_downloaded": 0
    },
    {
      "day": "DAY 2",
      "title": "Day 2 - 基礎：區塊鏈錢包",
      "url": "https://ithelp.ithome.com.tw/articles/10316715",
      "file": "ironman-6262-days/day02-day-2-基礎-區塊鏈錢包.md",
      "sections": 6,
      "raw_len": 2359,
      "md_len": 3684,
      "coverage_ratio": 1.562,
      "images_in_article": 5,
      "images_downloaded": 5
    },
    {
      "day": "DAY 3",
      "title": "Day 3 - 基礎：操作測試鏈應用",
      "url": "https://ithelp.ithome.com.tw/articles/10316725",
      "file": "ironman-6262-days/day03-day-3-基礎-操作測試鏈應用.md",
      "sections": 6,
      "raw_len": 2740,
      "md_len": 4409,
      "coverage_ratio": 1.609,
      "images_in_article": 10,
      "images_downloaded": 10
    },
    {
      "day": "DAY 4",
      "title": "Day 4 - Web3 與前端：實作第一個 DApp",
      "url": "https://ithelp.ithome.com.tw/articles/10317706",
      "file": "ironman-6262-days/day04-day-4-web3-與前端-實作第一個-dapp.md",
      "sections": 8,
      "raw_len": 4775,
      "md_len": 6282,
      "coverage_ratio": 1.316,
      "images_in_article": 5,
      "images_downloaded": 5
    },
    {
      "day": "DAY 5",
      "title": "Day 5 - Web3 與前端：幫 DApp 加功能",
      "url": "https://ithelp.ithome.com.tw/articles/10317865",
      "file": "ironman-6262-days/day05-day-5-web3-與前端-幫-dapp-加功能.md",
      "sections": 7,
      "raw_len": 5789,
      "md_len": 8073,
      "coverage_ratio": 1.395,
      "images_in_article": 6,
      "images_downloaded": 6
    },
    {
      "day": "DAY 6",
      "title": "Day 6 - Web3 與前端：RainbowKit + Wallet Connect",
      "url": "https://ithelp.ithome.com.tw/articles/10318382",
      "file": "ironman-6262-days/day06-day-6-web3-與前端-rainbowkit-wallet-connect.md",
      "sections": 6,
      "raw_len": 5555,
      "md_len": 8357,
      "coverage_ratio": 1.504,
      "images_in_article": 13,
      "images_downloaded": 13
    },
    {
      "day": "DAY 7",
      "title": "Day 7 - Web3 與前端：實作錢包登入 Part 1",
      "url": "https://ithelp.ithome.com.tw/articles/10319096",
      "file": "ironman-6262-days/day07-day-7-web3-與前端-實作錢包登入-part-1.md",
      "sections": 7,
      "raw_len": 7827,
      "md_len": 10008,
      "coverage_ratio": 1.279,
      "images_in_article": 6,
      "images_downloaded": 6
    },
    {
      "day": "DAY 8",
      "title": "Day 8 - Web3 智能合約基礎",
      "url": "https://ithelp.ithome.com.tw/articles/10320152",
      "file": "ironman-6262-days/day08-day-8-web3-智能合約基礎.md",
      "sections": 7,
      "raw_len": 9033,
      "md_len": 11209,
      "coverage_ratio": 1.241,
      "images_in_article": 3,
      "images_downloaded": 3
    },
    {
      "day": "DAY 9",
      "title": "Day 9 - Web3 與後端：實作錢包登入 Part 2",
      "url": "https://ithelp.ithome.com.tw/articles/10321485",
      "file": "ironman-6262-days/day09-day-9-web3-與後端-實作錢包登入-part-2.md",
      "sections": 6,
      "raw_len": 8312,
      "md_len": 9437,
      "coverage_ratio": 1.135,
      "images_in_article": 0,
      "images_downloaded": 0
    },
    {
      "day": "DAY 10",
      "title": "Day 10 - Web3 與後端：建立錢包與取得 Token Balance",
      "url": "https://ithelp.ithome.com.tw/articles/10322595",
      "file": "ironman-6262-days/day10-day-10-web3-與後端-建立錢包與取得-token-balance.md",
      "sections": 5,
      "raw_len": 7555,
      "md_len": 10061,
      "coverage_ratio": 1.332,
      "images_in_article": 8,
      "images_downloaded": 8
    },
    {
      "day": "DAY 11",
      "title": "Day 11 - Web3 與後端：簽名與發送交易",
      "url": "https://ithelp.ithome.com.tw/articles/10323062",
      "file": "ironman-6262-days/day11-day-11-web3-與後端-簽名與發送交易.md",
      "sections": 6,
      "raw_len": 5056,
      "md_len": 6112,
      "coverage_ratio": 1.209,
      "images_in_article": 3,
      "images_downloaded": 3
    },
    {
      "day": "DAY 12",
      "title": "Day 12 - Web 3 與 App：創多鏈錢包與發送交易",
      "url": "https://ithelp.ithome.com.tw/articles/10324026",
      "file": "ironman-6262-days/day12-day-12-web-3-與-app-創多鏈錢包與發送交易.md",
      "sections": 5,
      "raw_len": 5572,
      "md_len": 6681,
      "coverage_ratio": 1.199,
      "images_in_article": 2,
      "images_downloaded": 2
    },
    {
      "day": "DAY 13",
      "title": "Day 13 - Web 3 與 App：代幣轉移、Call Data 與 EIP-1559",
      "url": "https://ithelp.ithome.com.tw/articles/10324716",
      "file": "ironman-6262-days/day13-day-13-web-3-與-app-代幣轉移-call-data-與-eip-1559.md",
      "sections": 7,
      "raw_len": 8600,
      "md_len": 10853,
      "coverage_ratio": 1.262,
      "images_in_article": 6,
      "images_downloaded": 6
    },
    {
      "day": "DAY 14",
      "title": "Day 14 - Web 3 與 App：ENS 域名與反向查詢",
      "url": "https://ithelp.ithome.com.tw/articles/10325709",
      "file": "ironman-6262-days/day14-day-14-web-3-與-app-ens-域名與反向查詢.md",
      "sections": 5,
      "raw_len": 4977,
      "md_len": 6665,
      "coverage_ratio": 1.339,
      "images_in_article": 5,
      "images_downloaded": 5
    },
    {
      "day": "DAY 15",
      "title": "Day 15 - Web3 與進階前端：Revoke Cash 與 Logs 查詢",
      "url": "https://ithelp.ithome.com.tw/articles/10326582",
      "file": "ironman-6262-days/day15-day-15-web3-與進階前端-revoke-cash-與-logs-查詢.md",
      "sections": 6,
      "raw_len": 7916,
      "md_len": 9686,
      "coverage_ratio": 1.224,
      "images_in_article": 5,
      "images_downloaded": 5
    },
    {
      "day": "DAY 16",
      "title": "Day 17 - Web3 與進階前端：Meta Transaction 免手續費交易",
      "url": "https://ithelp.ithome.com.tw/articles/10327464",
      "file": "ironman-6262-days/day16-day-17-web3-與進階前端-meta-transaction-免手續費交易.md",
      "sections": 6,
      "raw_len": 7926,
      "md_len": 11213,
      "coverage_ratio": 1.415,
      "images_in_article": 12,
      "images_downloaded": 12
    },
    {
      "day": "DAY 17",
      "title": "Day 16 - Web3 與進階前端：瀏覽器錢包 Extension 原理",
      "url": "https://ithelp.ithome.com.tw/articles/10327465",
      "file": "ironman-6262-days/day17-day-16-web3-與進階前端-瀏覽器錢包-extension-原理.md",
      "sections": 6,
      "raw_len": 5955,
      "md_len": 7758,
      "coverage_ratio": 1.303,
      "images_in_article": 4,
      "images_downloaded": 4
    },
    {
      "day": "DAY 18",
      "title": "Day 18 - Web3 與進階後端：發送更複雜的交易",
      "url": "https://ithelp.ithome.com.tw/articles/10329344",
      "file": "ironman-6262-days/day18-day-18-web3-與進階後端-發送更複雜的交易.md",
      "sections": 6,
      "raw_len": 6238,
      "md_len": 8175,
      "coverage_ratio": 1.311,
      "images_in_article": 5,
      "images_downloaded": 5
    },
    {
      "day": "DAY 19",
      "title": "Day 19 - Web3 與進階後端：同時發送大量交易",
      "url": "https://ithelp.ithome.com.tw/articles/10330125",
      "file": "ironman-6262-days/day19-day-19-web3-與進階後端-同時發送大量交易.md",
      "sections": 7,
      "raw_len": 8511,
      "md_len": 10137,
      "coverage_ratio": 1.191,
      "images_in_article": 4,
      "images_downloaded": 4
    },
    {
      "day": "DAY 20",
      "title": "Day 20 - Web3 與進階後端：實作即時 ERC-20 Balance",
      "url": "https://ithelp.ithome.com.tw/articles/10330773",
      "file": "ironman-6262-days/day20-day-20-web3-與進階後端-實作即時-erc-20-balance.md",
      "sections": 7,
      "raw_len": 11283,
      "md_len": 13760,
      "coverage_ratio": 1.22,
      "images_in_article": 7,
      "images_downloaded": 7
    },
    {
      "day": "DAY 21",
      "title": "Day 21 - Web3 與進階後端：交易歷史資料整理",
      "url": "https://ithelp.ithome.com.tw/articles/10331449",
      "file": "ironman-6262-days/day21-day-21-web3-與進階後端-交易歷史資料整理.md",
      "sections": 8,
      "raw_len": 10834,
      "md_len": 13990,
      "coverage_ratio": 1.291,
      "images_in_article": 9,
      "images_downloaded": 9
    },
    {
      "day": "DAY 22",
      "title": "Day 22 - Web3 與進階 App：交易管理與 Mempool 監聽",
      "url": "https://ithelp.ithome.com.tw/articles/10332160",
      "file": "ironman-6262-days/day22-day-22-web3-與進階-app-交易管理與-mempool-監聽.md",
      "sections": 7,
      "raw_len": 7482,
      "md_len": 10238,
      "coverage_ratio": 1.368,
      "images_in_article": 10,
      "images_downloaded": 10
    },
    {
      "day": "DAY 23",
      "title": "Day 23 - Web3 與進階 App：Wallet Connect 協議與實作",
      "url": "https://ithelp.ithome.com.tw/articles/10332768",
      "file": "ironman-6262-days/day23-day-23-web3-與進階-app-wallet-connect-協議與實作.md",
      "sections": 6,
      "raw_len": 7962,
      "md_len": 9470,
      "coverage_ratio": 1.189,
      "images_in_article": 2,
      "images_downloaded": 2
    },
    {
      "day": "DAY 24",
      "title": "Day 24 - Web3 與進階 App：DApp 瀏覽器實作",
      "url": "https://ithelp.ithome.com.tw/articles/10333681",
      "file": "ironman-6262-days/day24-day-24-web3-與進階-app-dapp-瀏覽器實作.md",
      "sections": 8,
      "raw_len": 10056,
      "md_len": 12019,
      "coverage_ratio": 1.195,
      "images_in_article": 2,
      "images_downloaded": 2
    },
    {
      "day": "DAY 25",
      "title": "Day 25 - Web3 與進階 App：Swap 功能實作",
      "url": "https://ithelp.ithome.com.tw/articles/10334206",
      "file": "ironman-6262-days/day25-day-25-web3-與進階-app-swap-功能實作.md",
      "sections": 7,
      "raw_len": 10811,
      "md_len": 12897,
      "coverage_ratio": 1.193,
      "images_in_article": 5,
      "images_downloaded": 5
    },
    {
      "day": "DAY 26",
      "title": "Day 26 - Web3 與資安：攻擊方式與資產保護（上）",
      "url": "https://ithelp.ithome.com.tw/articles/10334895",
      "file": "ironman-6262-days/day26-day-26-web3-與資安-攻擊方式與資產保護-上.md",
      "sections": 10,
      "raw_len": 4140,
      "md_len": 6028,
      "coverage_ratio": 1.456,
      "images_in_article": 11,
      "images_downloaded": 11
    },
    {
      "day": "DAY 27",
      "title": "Day 27 - Web3 與資安：攻擊方式與資產保護（下）",
      "url": "https://ithelp.ithome.com.tw/articles/10335476",
      "file": "ironman-6262-days/day27-day-27-web3-與資安-攻擊方式與資產保護-下.md",
      "sections": 11,
      "raw_len": 4805,
      "md_len": 6963,
      "coverage_ratio": 1.449,
      "images_in_article": 12,
      "images_downloaded": 12
    },
    {
      "day": "DAY 28",
      "title": "Day 28 - Web3 與資安：私鑰保存與備份",
      "url": "https://ithelp.ithome.com.tw/articles/10335962",
      "file": "ironman-6262-days/day28-day-28-web3-與資安-私鑰保存與備份.md",
      "sections": 14,
      "raw_len": 3465,
      "md_len": 5033,
      "coverage_ratio": 1.453,
      "images_in_article": 10,
      "images_downloaded": 10
    },
    {
      "day": "DAY 29",
      "title": "Day 29 - Web3 與前沿技術：基礎建設與去中心化應用",
      "url": "https://ithelp.ithome.com.tw/articles/10336560",
      "file": "ironman-6262-days/day29-day-29-web3-與前沿技術-基礎建設與去中心化應用.md",
      "sections": 12,
      "raw_len": 5019,
      "md_len": 7311,
      "coverage_ratio": 1.457,
      "images_in_article": 6,
      "images_downloaded": 6
    },
    {
      "day": "DAY 30",
      "title": "Day 30 - Web3 與前沿技術：密碼學與應用",
      "url": "https://ithelp.ithome.com.tw/articles/10336862",
      "file": "ironman-6262-days/day30-day-30-web3-與前沿技術-密碼學與應用.md",
      "sections": 12,
      "raw_len": 6741,
      "md_len": 8718,
      "coverage_ratio": 1.293,
      "images_in_article": 6,
      "images_downloaded": 6
    }
  ],
  "failed_images": []
}